desto/__init__.py
desto/_version.py
desto/notifications.py
desto/app/config.py
desto/app/dashboard.py
desto/app/favorites_ui.py
desto/app/sessions.py
desto/app/ui.py
desto/app/ui_elements.py
desto/cli/README.md
desto/cli/__init__.py
desto/cli/cli.py
desto/cli/main.py
desto/cli/scripts.py
desto/cli/session_manager.py
desto/cli/sessions.py
desto/cli/utils.py
desto/redis/__init__.py
desto/redis/at_job_manager.py
desto/redis/client.py
desto/redis/desto_manager.py
desto/redis/favorites_manager.py
desto/redis/job_manager.py
desto/redis/models.py
desto/redis/pubsub.py
desto/redis/session_manager.py
desto-0.4.10.dist-info/METADATA
desto-0.4.10.dist-info/WHEEL
desto-0.4.10.dist-info/entry_points.txt
desto-0.4.10.dist-info/licenses/LICENSE
desto-0.4.10.dist-info/RECORD
