Metadata-Version: 2.4
Name: desto
Version: 0.4.10
Summary: tmux session manager
License-File: LICENSE
Requires-Python: >=3.11
Requires-Dist: ipython>=9.2.0
Requires-Dist: loguru>=0.7.3
Requires-Dist: nicegui>=2.16.1
Requires-Dist: pre-commit>=4.2.0
Requires-Dist: psutil>=7.0.0
Requires-Dist: pytest-instafail>=0.5.0
Requires-Dist: pytest-xdist>=3.2.0
Requires-Dist: pytest>=8.3.5
Requires-Dist: redis>=4.0.0
Requires-Dist: rich>=13.0.0
Requires-Dist: twine>=6.1.0
Requires-Dist: typer>=0.12.0
Provides-Extra: dev
Requires-Dist: requests>=2.31.0; extra == 'dev'
Requires-Dist: ruff>=0.1.0; extra == 'dev'
Provides-Extra: docs
Requires-Dist: loguru>=0.7.3; extra == 'docs'
Requires-Dist: mkdocs-htmlproofer-plugin>=1.2.1; extra == 'docs'
Requires-Dist: mkdocs-include-markdown-plugin>=6.0.0; extra == 'docs'
Requires-Dist: mkdocs-material>=9.6.19; extra == 'docs'
Requires-Dist: mkdocs>=1.6.1; extra == 'docs'
Requires-Dist: mkdocstrings-python>=1.18.2; extra == 'docs'
Requires-Dist: mkdocstrings>=0.30.0; extra == 'docs'
Requires-Dist: pymdown-extensions>=10.16.1; extra == 'docs'
